_inner.cpython-38-darwin.so
edbscan/__init__.py
edbscan/_inner.cpython-38-darwin.so
edbscan/_inner.py
edbscan/main.py
edbscan-0.0.1.dist-info/LICENSE
edbscan-0.0.1.dist-info/METADATA
edbscan-0.0.1.dist-info/WHEEL
edbscan-0.0.1.dist-info/top_level.txt
edbscan-0.0.1.dist-info/RECORD
