Metadata-Version: 2.1
Name: edbscan
Version: 0.0.1
Summary: Enforced Density -Based Spatial Clustering of Applications with Noise.
Home-page: https://github.com/RubenPants/EDBSCAN
Author: Ruben Broekx
License: UNKNOWN
Platform: UNKNOWN
License-File: LICENSE
Requires-Dist: scikit-learn (~=1.0.0)
Requires-Dist: numpy (~=1.21.2)
